loladb-0.1.0.dist-info/METADATA
loladb-0.1.0.dist-info/WHEEL
loladb/__init__.py
loladb/client.py
loladb/loladb.cpython-311-darwin.so
loladb-0.1.0.dist-info/RECORD
